halfadder.vhd
LIBRARY IEEE;
USE IEEE.std_logic_1164.all;
USE IEEE.std_logic_arith.all;

ENTITY HALFADD IS
PORT ( A, B : IN BIT;
SUM, CARRY : OUT BIT);
END HALFADD;

ARCHITECTURE behave OF HALFADD IS
BEGIN
SUM <= A XOR B;
CARRY <= A AND B;
END behave;

fulladderstruct.vhd
LIBRARY IEEE;
USE IEEE.std_logic_1164.all;
USE IEEE.std_logic_arith.all;
USE work.all;

ENTITY ORGATE IS
PORT ( A, B : IN BIT;
Z : OUT BIT);
END ORGATE;

ARCHITECTURE behave OF ORGATE IS
BEGIN
Z <= A OR B;
END behave;


entity FULLADD is
	port(A, B, CIN : in bit;
	SUM, CARRY : out bit);
end FULLADD;

architecture STRUCT of FULLADD is
	signal I1, I2, I3 : bit;

	component HALFADD
	port(A,B        : in bit  ;SUM, CARRY : out bit  );
	end   component;

	component ORGATE
	port(A,B : in bit;Z: out bit);
	end component;


begin
	
	U1:HALFADD port map(A,B,I1,I2);
	U2:HALFADD port map(I1,CIN,SUM,I3);
	U3:ORGATE port map(I3,I2,CARRY);

end STRUCT;

vcds/fulladd.vcd
$date
	Sun Jun  6 16:13:19 2021
$end
$version
	QuestaSim Version 10.6c_1
$end
$timescale
	1ns
$end

$scope module fulladd $end
$var wire 1 ! A $end
$var wire 1 " B $end
$var wire 1 # CIN $end
$var wire 1 $ SUM $end
$var wire 1 % CARRY $end
$upscope $end
$enddefinitions $end
#0
$dumpvars
0!
0"
0#
0$
0%
$end
#100
1"
#102
1$
#200
1!
0"
#300
1"
#302
0$
1%
#400
0!
0"
1#
#402
1$
0%
#500
1"
#502
0$
1%
#600
1!
0"
#700
1"
#702
1$
#800
0!
0"
0#
#802
0$
0%
