siebensegment.vhd
LIBRARY IEEE;
USE IEEE.std_logic_1164.all;

ENTITY SIEBENSEGMENT IS
port(NUM: in bit_vector(3 downto 0);
RESET: in BIT;
OUTPUT: out bit_vector(0 to 6));
end SIEBENSEGMENT;

ARCHITECTURE BEHAVIOUR OF SIEBENSEGMENT IS
BEGIN PROCESS(NUM, RESET)
BEGIN
if RESET = '1' then
  OUTPUT <= "1111111";
else
  CASE NUM is
    when "0000" =>
        OUTPUT <= "0000001"; -- 0
    when "0001" =>
        OUTPUT <= "1001111"; -- 1
    when "0010" =>
        OUTPUT <= "0010010"; -- 2
    when "0011" =>
        OUTPUT <= "0000110"; -- 3
    when "0100" =>
        OUTPUT <= "0001100"; -- 4
    when "0101" =>
        OUTPUT <= "0100100"; -- 5
    when "0110" =>
        OUTPUT <= "0100000"; -- 6
    when "0111" =>
        OUTPUT <= "0001111"; -- 7
    when "1000" =>
        OUTPUT <= "0000000"; -- 8
    when "1001" =>
        OUTPUT <= "0000100"; -- 9
    when others =>
        OUTPUT <= "0111000"; -- F für Fehler anzeigen
  END CASE;
end if;
END PROCESS;
END BEHAVIOUR;

testsiebensegment.vhd
LIBRARY IEEE;
USE IEEE.std_logic_1164.all;
use IEEE.NUMERIC_STD.all;

ENTITY siebensegmenttest IS END siebensegmenttest;

ARCHITECTURE testdriver OF siebensegmenttest IS 
  SIGNAL NUM:BIT_VECTOR(3 DOWNTO 0);
  SIGNAL RESET:BIT;
  SIGNAL OUTPUT:BIT_VECTOR(0 to 6);

  SIGNAL clk: BIT := '0';

  COMPONENT SIEBENSEGMENT PORT(
    NUM: in bit_vector(3 downto 0);
    RESET: in BIT;
    OUTPUT: out bit_vector(0 to 6));
  END COMPONENT;

  FOR ALL:SIEBENSEGMENT USE ENTITY work.siebensegment(behaviour);

BEGIN
  DuT : SIEBENSEGMENT PORT MAP(NUM, RESET, OUTPUT);
  clk <= NOT clk AFTER 20 ns;

  stimulus: PROCESS
    BEGIN
    RESET <= '0';  -- Eingänge zurücksetzten
    NUM <= "0000"; -- Eingänge zurücksetzten

    WAIT UNTIL clk'EVENT AND clk= '1';

    -- Alle Zahlen von 0-15 durchtesten
    for i in 0 to 15 loop
       NUM <= To_bitvector(std_logic_vector(to_unsigned(i, 4)));
       WAIT UNTIL clk'EVENT AND clk= '1';
    end loop;

    RESET <= '1'; -- RESET Testen
    WAIT UNTIL clk'EVENT AND clk= '1';
  END PROCESS;

END testdriver;

vcds/siebensegment.vcd
$date
	Sun Jun  6 15:59:42 2021
$end
$version
	QuestaSim Version 10.6c_1
$end
$timescale
	1ns
$end

$scope module siebensegmenttest $end
$var wire 1 ! NUM [3] $end
$var wire 1 " NUM [2] $end
$var wire 1 # NUM [1] $end
$var wire 1 $ NUM [0] $end
$var wire 1 % RESET $end
$var wire 1 & OUTPUT [0] $end
$var wire 1 ' OUTPUT [1] $end
$var wire 1 ( OUTPUT [2] $end
$var wire 1 ) OUTPUT [3] $end
$var wire 1 * OUTPUT [4] $end
$var wire 1 + OUTPUT [5] $end
$var wire 1 , OUTPUT [6] $end
$upscope $end
$enddefinitions $end
#0
$dumpvars
0%
0!
0"
0#
0$
0&
0'
0(
0)
0*
0+
1,
$end
#60
1$
1+
1*
1)
1&
#100
0$
1#
0,
0*
0)
1(
0&
#140
1$
1*
0(
#180
0$
0#
1"
0+
1)
#220
1$
0)
1'
#260
0$
1#
0*
#300
1$
1,
1+
1*
1)
0'
#340
0$
0#
0"
1!
0,
0+
0*
0)
#380
1$
1*
#420
0$
1#
0*
1)
1(
1'
#460
1$
#500
0$
0#
1"
#540
1$
#580
0$
1#
#620
1$
#660
1%
1,
1+
1*
1&
#700
0$
0#
0"
0!
0%
0+
0*
0)
0(
0'
0&
